biip/__init__.py
biip/_config.py
biip/_exceptions.py
biip/_parser.py
biip/_typing.py
biip/checksums.py
biip/gln.py
biip/gs1_digital_link_uris.py
biip/gs1_element_strings.py
biip/gs1_messages.py
biip/gtin.py
biip/py.typed
biip/rcn.py
biip/sscc.py
biip/symbology.py
biip/upc.py
biip/gs1_application_identifiers/__init__.py
biip/gs1_application_identifiers/_application_identifiers.json
biip/gs1_prefixes/__init__.py
biip/gs1_prefixes/_company_prefix_trie.json.lzma
biip/gs1_prefixes/_prefix_trie.json.lzma
biip-5.0.0.dist-info/METADATA
biip-5.0.0.dist-info/WHEEL
biip-5.0.0.dist-info/licenses/LICENSE
biip-5.0.0.dist-info/RECORD
