Metadata-Version: 2.4
Name: biip
Version: 5.0.0
Summary: Biip interprets the data in barcodes.
Project-URL: Homepage, https://github.com/jodal/biip
Project-URL: Repository, https://github.com/jodal/biip
Project-URL: Documentation, https://biip.readthedocs.io
Author-email: Stein Magnus Jodal <stein.magnus@jodal.no>
License-Expression: Apache-2.0
License-File: LICENSE
Keywords: barcodes,ean,gs1,gtin,isbn,upc
Classifier: Development Status :: 5 - Production/Stable
Classifier: Intended Audience :: Developers
Classifier: Topic :: Software Development :: Libraries
Requires-Python: >=3.10
Requires-Dist: typing-extensions>=4.1; python_version < '3.11'
Provides-Extra: money
Requires-Dist: py-moneyed>=0.8; extra == 'money'
